ols_py/__init__.py
ols_py/client.py
ols_py/instances.py
ols_py/py.typed
ols_py/schemas/__init__.py
ols_py/schemas/common.py
ols_py/schemas/requests.py
ols_py/schemas/responses.py
ols_py-1.1.0.dist-info/LICENCE
ols_py-1.1.0.dist-info/METADATA
ols_py-1.1.0.dist-info/WHEEL
ols_py-1.1.0.dist-info/RECORD
