Metadata-Version: 2.1
Name: ols-py
Version: 1.1.0
Summary: Python client for the Ontology Lookup Service
Home-page: https://ahida-development.github.io/ols-py
License: MIT
Author: Marius Mather
Author-email: marius.mather@sydney.edu.au
Requires-Python: >=3.10.1,<4.0
Classifier: Development Status :: 5 - Production/Stable
Classifier: Intended Audience :: Developers
Classifier: License :: OSI Approved :: MIT License
Classifier: Operating System :: OS Independent
Classifier: Programming Language :: Python
Classifier: Programming Language :: Python :: 3
Classifier: Programming Language :: Python :: 3.11
Classifier: Programming Language :: Python :: 3.12
Classifier: Programming Language :: Python :: 3.10
Classifier: Topic :: Software Development :: Libraries :: Python Modules
Classifier: Typing :: Typed
Requires-Dist: pydantic (>=2.1.1,<3.0.0)
Requires-Dist: requests (>=2.0,<3.0)
Project-URL: Documentation, https://ahida-development.github.io/ols-py
Project-URL: Repository, https://github.com/ahida-development/ols-py
